{
  "ADD_DEPARTMENT_AUTH": "smt-base-A",
  "ADD_MODULE": "smt-base-A",
  "ADD_MODULE_LIST": "smt-base-A",
  "ADD_POST": "smt-base-A",
  "ADD_ROLE": "smt-base-A",
  "ADD_USER_AND_ACCOUNT": "smt-base-A",
  "B_P_ANALYSIS_LAYOUT": "smt-cfg-A",
  "B_P_C_CONFIG_PAGE_ALL": "smt-base-A",
  "CREATE_SYS_MENU_ITEM": "smt-base-A",
  "DELETE_MODULE": "smt-base-A",
  "DELETE_MODULE_FUNC": "smt-base-A",
  "DELETE_MULTILANGUAGE": "smt-base-A",
  "DELETE_POST": "smt-base-A",
  "DELETE_ROLE": "smt-base-A",
  "GET_ATTRIBUTE_TREE_SELECT": "smt-base-A",
  "GET_AUTH_LAYOUT_STRUCTURE": "smt-base-A",
  "GET_AUTH_LAYOUT_STRUCTURE_SHOW": "smt-base-A",
  "GET_AUTH_PAGE_LIST": "smt-base-A",
  "GET_AUTH_PAGE_LIST_SHOW": "smt-base-A",
  "GET_BUSINESS_MAIN_LIST": "smt-cfg-A",
  "GET_BUSINESS_OBJECT_LIST": "smt-cfg-A",
  "GET_DATA_MODELING_TABLE": "smt-cfg-A",
  "GET_DATADICTIONARY_MULTILANGUAGE": "smt-base-A",
  "GET_DEPARTMENT": "smt-base-A",
  "GET_DM_COLUMNS_LIST": "smt-cfg-A",
  "GET_DM_COLUMNS_LIST_ADD": "smt-cfg-A",
  "GET_DM_RESOURCE_PARAMS_LIST": "smt-cfg-A",
  "GET_DM_SQL_LIST": "smt-cfg-A",
  "GET_FUNC_TREE": "smt-cfg-A",
  "GET_LAYOUT_STRUCTURE": "smt-cfg-A",
  "GET_LAYOUT_STRUCTURE_AUTH": "smt-base-A",
  "GET_MENU_AUTH_TREE": "smt-base-A",
  "GET_MENU_AUTH_TREE_SHOW": "smt-base-A",
  "GET_MENU_BY_ID": "smt-base-A",
  "GET_MENU_PAGE_CHILD": "smt-base-A",
  "GET_MENU_PAGE_LAYOUTS_BY_MENU_ID": "smt-base-A",
  "GET_MENU_PAGE_TREE": "smt-base-A",
  "GET_MODULE_LIST": "smt-base-A",
  "GET_MODULE_LIST_WORK": "smt-base-A",
  "GET_MODULE_LIST2": "smt-base-A",
  "GET_MODULE_TREE": "smt-base-A",
  "GET_MODULE_TREE_SELECT_DATA_MODELING": "smt-cfg-A",
  "GET_MODULE_TREE_SELECT_SQL_MODELING": "smt-cfg-A",
  "GET_MULTILANGUAGE_LIST": "smt-base-A",
  "GET_PAGE_TREE": "smt-base-A",
  "GET_POST_INFO": "smt-base-A",
  "GET_PREMISSION_ORG_TREE": "smt-base-A",
  "GET_PUBLISH_LAYOUT_TREE_DATA": "smt-base-A",
  "GET_PUBLISH_MENU_TREE_DATA": "smt-base-A",
  "GET_PUBLISH_SYS_MODULE_TREE_DATA": "smt-base-A",
  "GET_ROLE_INFO": "smt-base-A",
  "GET_ROLE_LINK_INFO": "smt-base-A",
  "GET_SMT_PAGE_LAYOUT_TREE": "smt-base-A",
  "GET_SYS_MENU_TREE": "smt-base-A",
  "GET_SYSTEM_DEPT": "smt-base-A",
  "GET_SYSTEM_USER": "smt-base-A",
  "GET_USER_ROLE_LINK_BY_ROLE": "smt-base-A",
  "LOG_OPERATION_1": "smt-base-A",
  "MDM_DEPARTMENT": "smt-base-A",
  "RESULT_RETURN": "smt-cfg-A",
  "SMT_IMP_ACCOUNT": "smt-base-A",
  "SMT_IMP_DATABASE_BUFFER": "smt-base-A",
  "SMT_IMP_DEPT": "smt-base-A",
  "SMT_IMP_DEPT_USER_LINK": "smt-base-A",
  "SMT_IMP_MODULE_ROLE_LINK": "smt-base-A",
  "SMT_IMP_POST": "smt-base-A",
  "SMT_IMP_PROJECT_BUFFER": "smt-base-A",
  "SMT_IMP_RES_USER_LINK": "smt-base-A",
  "SMT_IMP_ROLE": "smt-base-A",
  "SMT_IMP_USER": "smt-base-A",
  "SMT_SETTING_FUNC": "smt-base-A",
  "SMT_SETTING_LAYOUT": "smt-base-A",
  "SMT_SETTING_LAYOUT_STRUCTURE": "smt-base-A",
  "SMT_SETTING_PAGE": "smt-base-A",
  "SY_INTERNATIONALIZATION": "smt-base-A",
  "SY_MODULE": "smt-base-A",
  "SY_MULTILANGUAGE": "smt-base-A",
  "SYS_AUTH_DATA": "smt-base-A",
  "SYS_AUTH_MODULE_FUNC": "smt-base-A",
  "SYS_AUTH_PAGE": "smt-base-A",
  "SYS_AUTH_PAGE_STRUCT": "smt-base-A",
  "SYS_AUTH_PERMISSION": "smt-base-A",
  "SYS_AUTH_RES_INIT": "smt-base-A",
  "SYS_MENU": "smt-base-A",
  "SYS_MENU_PAGE_REL": "smt-base-A",
  "UPDATE_MULTILANGUAGE_ENABLE": "smt-base-A",
  "UPDATE_POST": "smt-base-A",
  "UPDATE_ROLE": "smt-base-A",
  "UPDATE_SYS_MENU_ITEM": "smt-base-A"
}
